cdk_lambda_layer_curl/__init__.py
cdk_lambda_layer_curl/py.typed
cdk_lambda_layer_curl/_jsii/__init__.py
cdk_lambda_layer_curl/_jsii/cdk-lambda-layer-curl@2.0.838.jsii.tgz
cdk_lambda_layer_curl-2.0.838.dist-info/LICENSE
cdk_lambda_layer_curl-2.0.838.dist-info/METADATA
cdk_lambda_layer_curl-2.0.838.dist-info/WHEEL
cdk_lambda_layer_curl-2.0.838.dist-info/top_level.txt
cdk_lambda_layer_curl-2.0.838.dist-info/RECORD
